Metadata-Version: 2.1
Name: sara-compis1-tools
Version: 0.0.7
Summary: A collection of tools for the Language Design course
Home-page: https://github.com/MGonza20/Compis_Lab4
Author: Sara Paguaga
Author-email: sara.paguaga@gmail.com
License: MIT
Keywords: Compiler
Classifier: Development Status :: 3 - Alpha
Classifier: Intended Audience :: Developers
Classifier: License :: OSI Approved :: MIT License
Classifier: Programming Language :: Python :: 3
License-File: LICENSE.txt
